{
  "publishAt": "2026-07-07T07:46:00.000Z",
  "market": "sa",
  "date": "2026-07-07",
  "item": {
    "id": "sa-20260707-sports",
    "category": "sports",
    "type": "text",
    "format": "markdown",
    "title": "صيف رياضي استثنائي: الأخضر في مونديال 2026 وكأس العالم للرياضات الإلكترونية يشعل الرياض",
    "body": "قلّما اجتمع للجمهور السعودي صيف بهذا الزخم: فبينما يخوض **المنتخب السعودي** غمار **كأس العالم 2026** في أمريكا الشمالية، تحتضن الرياض النسخة الجديدة من **كأس العالم للرياضات الإلكترونية (EWC)**، أكبر حدث من نوعه على مستوى العالم.\n\n## الأخضر في مونديال الـ48 منتخبًا\n\nحجز الأخضر مقعده في المونديال بعد مشوار تصفيات حاسم أُنهي على أرضه في جدة، ليسجل حضوره **السابع** في تاريخ كأس العالم. النسخة الحالية استثنائية بكل المقاييس: أول مونديال بمشاركة **48 منتخبًا**، وأول بطولة تستضيفها ثلاث دول معًا (الولايات المتحدة وكندا والمكسيك)، وتمتد مبارياتها حتى النهائي المقرر في **19 يوليو** على ملعب «ميتلايف» في نيوجيرسي. وبعيدًا عن النتائج، فإن كل دقيقة يلعبها الأخضر في هذا العرس الكروي تمثل بروفة مبكرة لموعد أكبر: **استضافة السعودية لكأس العالم 2034**، التي بدأ العمل على ملاعبها ومنشآتها فعليًا.\n\n## الرياض عاصمة الألعاب الإلكترونية\n\nفي المقابل، يعود **كأس العالم للرياضات الإلكترونية** إلى «بوليفارد رياض سيتي» هذا الصيف، بجوائز تُعد الأضخم في تاريخ اللعبة التنافسية — إذ تجاوزت في النسخ الأخيرة **70 مليون دولار** — وبمشاركة أبرز الأندية العالمية في عشرات الألعاب، من «Dota 2» و«Counter-Strike» إلى ألعاب القتال وسباقات السيارات الافتراضية.\n\nالحدث ليس مجرد بطولة، بل واجهة لاستراتيجية سعودية متكاملة في قطاع الألعاب تقودها مجموعة **Savvy Games** المملوكة لصندوق الاستثمارات العامة، وتستهدف تحويل المملكة إلى مركز عالمي لصناعة تُقدّر قيمتها بمئات المليارات. ونجاح نادي **فالكونز (Team Falcons)** السعودي في انتزاع لقب الأندية في النسخ الماضية منح الجمهور المحلي بطلًا يهتف له على أرضه.\n\n## ماذا يعني هذا الصيف للرياضة السعودية؟\n\n- **حضور عالمي مزدوج**: منتخب على أكبر مسرح كروي، وعاصمة تستضيف أكبر مسرح إلكتروني.\n- **استثمار في الجماهير الشابة**: أكثر من ثلثي السعوديين يمارسون الألعاب الإلكترونية، ما يجعل EWC حدثًا جماهيريًا بامتياز.\n- **بناء نحو 2034**: كل بطولة تُنظَّم أو يُشارَك فيها اليوم هي خطوة في مشروع رياضي أطول أمدًا.\n\nسواء كنت من جمهور المستطيل الأخضر أو من عشاق الشاشات، فهذا الصيف يقدم لك تذكرة في الصف الأول.",
    "tier": "free"
  }
}
