{
  "publishAt": "2026-07-24T19:37:00.000Z",
  "market": "de",
  "date": "2026-07-24",
  "item": {
    "id": "de-20260724-news-4",
    "category": "news",
    "type": "text",
    "format": "markdown",
    "title": "Fachkräfteengpässe: Warum der Renteneintritt der Babyboomer Deutschlands Arbeitswelt verändert",
    "body": "Deutschland steht vor einem tiefgreifenden Wandel am Arbeitsmarkt. Die geburtenstarken Jahrgänge der 1950er- und 1960er-Jahre – die sogenannten Babyboomer – verabschieden sich Schritt für Schritt in den Ruhestand. Nach gängigen Schätzungen von Arbeitsmarktforschern könnten dem Land bis 2030 rund zwei Millionen Fachkräfte fehlen. Was zunächst wie eine abstrakte Zahl klingt, ist längst im Alltag vieler Betriebe, Behörden und Haushalte spürbar.\n\n## Ein demografischer Umbruch mit Ansage\n\nDer Fachkräftemangel kommt nicht überraschend. Seit Jahrzehnten ist bekannt, dass die Babyboomer die mit Abstand größte Generation auf dem deutschen Arbeitsmarkt stellen. Jedes Jahr erreichen nun deutlich mehr Beschäftigte das Rentenalter, als junge Menschen neu ins Erwerbsleben eintreten. Diese Lücke lässt sich rechnerisch kaum schließen: Die nachrückenden Jahrgänge sind schlicht kleiner.\n\nBesonders betroffen sind Bereiche, die schon heute unter Personalknappheit leiden:\n\n- **Pflege und Gesundheit:** Der Bedarf wächst durch die alternde Gesellschaft, während gleichzeitig erfahrene Kräfte ausscheiden.\n- **Handwerk und Bau:** Viele Betriebe finden keine Nachfolger und müssen Aufträge ablehnen oder Wartezeiten verlängern.\n- **IT und Technik:** Digitalisierungsprojekte verzögern sich, weil Spezialistinnen und Spezialisten fehlen.\n- **Bildung und öffentlicher Dienst:** Schulen, Kitas und Verwaltungen ringen um qualifiziertes Personal.\n\n## Was der Engpass für Wirtschaft und Alltag bedeutet\n\nFehlende Fachkräfte sind nicht nur ein Problem einzelner Unternehmen. Ökonomen weisen darauf hin, dass ein anhaltender Arbeitskräftemangel das Wachstumspotenzial der gesamten Volkswirtschaft dämpfen kann. Wenn Stellen monatelang unbesetzt bleiben, verzögern sich Projekte, steigen Kosten und sinkt mitunter die Qualität von Dienstleistungen.\n\nAuch die Sozialsysteme geraten unter Druck: Weniger Beitragszahler müssen die Renten, Gesundheits- und Pflegeleistungen einer wachsenden Zahl älterer Menschen mitfinanzieren. Für Beschäftigte kann der Wandel zugleich Chancen bedeuten – etwa bessere Verhandlungspositionen bei Gehalt und Arbeitsbedingungen, da Unternehmen stärker um Personal werben müssen.\n\n## Drei Strategien gegen die Lücke\n\nUnternehmen und Politik setzen im Wesentlichen auf drei Hebel, um die entstehenden Lücken zu schließen.\n\n### 1. Automatisierung und Digitalisierung\n\nWo Menschen fehlen, sollen Maschinen und Software entlasten. In der Industrie übernehmen Roboter zunehmend repetitive Aufgaben, in Büros helfen digitale Werkzeuge bei Routinetätigkeiten, und auch in der Logistik oder der Landwirtschaft schreitet die Automatisierung voran. Fachleute betonen allerdings: Technik ersetzt selten ganze Berufe, sondern verändert vor allem Tätigkeitsprofile. Gerade in sozialen Berufen wie der Pflege bleibt der Mensch unverzichtbar – Technik kann dort höchstens unterstützen, etwa bei Dokumentation oder körperlich belastenden Aufgaben.\n\n### 2. Zuwanderung qualifizierter Arbeitskräfte\n\nOhne Zuwanderung würde die Zahl der Erwerbspersonen in Deutschland deutlich schneller sinken. Mit dem reformierten Fachkräfteeinwanderungsgesetz will die Politik die Anwerbung internationaler Arbeitskräfte erleichtern, etwa durch vereinfachte Anerkennung ausländischer Abschlüsse und neue Wege wie die Chancenkarte. In der Praxis bleiben jedoch Hürden: lange Visaverfahren, Sprachbarrieren, Wohnungsknappheit und die Frage, wie gut Integration vor Ort gelingt. Viele Unternehmen investieren deshalb selbst in Sprachkurse, Mentoring und Unterstützung bei Behördengängen.\n\n### 3. Weiterbildung und Umschulung\n\nDer dritte Hebel liegt in der vorhandenen Erwerbsbevölkerung. Beschäftigte, deren Tätigkeiten sich durch Digitalisierung wandeln, sollen für neue Aufgaben qualifiziert werden. Dazu zählen betriebliche Weiterbildungen, geförderte Umschulungen und Teilqualifizierungen für Menschen ohne formalen Berufsabschluss. Auch bislang wenig genutzte Potenziale rücken in den Blick: mehr Arbeitsstunden für Teilzeitkräfte, die dies wünschen, bessere Vereinbarkeit von Familie und Beruf sowie flexible Modelle für ältere Beschäftigte, die über das Rentenalter hinaus arbeiten möchten.\n\n## Länger arbeiten, anders arbeiten?\n\nDer Umgang mit dem Renteneintritt der Babyboomer wirft auch gesellschaftliche Grundsatzfragen auf. Sollen Menschen künftig länger arbeiten? Wie lassen sich Erfahrung und Wissen ausscheidender Fachkräfte im Betrieb halten – etwa durch Tandems aus älteren und jüngeren Beschäftigten? Und wie attraktiv sind Ausbildung und duale Berufe für junge Menschen, wenn viele zunächst ein Studium anstreben?\n\nEinige Betriebe experimentieren bereits mit Antworten: Sie bieten Wiedereinstiegsprogramme für Rentnerinnen und Rentner, reduzieren körperliche Belastungen durch bessere Arbeitsgestaltung oder werben mit Vier-Tage-Modellen um Nachwuchs. Ob solche Ansätze in der Breite tragen, wird sich in den kommenden Jahren zeigen.\n\n## Ausblick: Ein Jahrzehnt der Anpassung\n\nDer demografische Wandel lässt sich nicht aufhalten, wohl aber gestalten. Die kommenden Jahre gelten unter Fachleuten als entscheidend: Gelingt es, Automatisierung, Zuwanderung und Qualifizierung klug zu kombinieren, kann Deutschland den Übergang abfedern. Bleiben die Anstrengungen hinter dem Bedarf zurück, drohen längere Wartezeiten bei Dienstleistungen, steigende Kosten und wachsender Druck auf die verbleibenden Beschäftigten.\n\nKlar ist: Der Ruhestand der Babyboomer ist kein kurzfristiges Konjunkturphänomen, sondern ein struktureller Umbruch. Er verändert, wie in Deutschland gearbeitet, ausgebildet und geplant wird – und betrifft damit letztlich alle, vom Auszubildenden bis zur Unternehmerin.\n\n*Hinweis: Die genannten Zahlen beruhen auf gängigen Schätzungen und Prognosen von Arbeitsmarktforschungseinrichtungen. Tatsächliche Entwicklungen können je nach wirtschaftlicher Lage und politischen Entscheidungen abweichen.*",
    "tier": "free"
  }
}
