{
  "publishAt": "2026-07-03T14:58:00.000Z",
  "market": "id",
  "date": "2026-07-03",
  "item": {
    "id": "id-20260703-culture",
    "category": "culture",
    "type": "text",
    "format": "markdown",
    "title": "Merayakan Jakarta: Semarak Budaya dan Sejarah di Ulang Tahun Ibu Kota",
    "body": "## Kota yang Merayakan Dirinya Sendiri\n\nSetiap 22 Juni, Jakarta memperingati hari jadinya—sebuah tradisi yang menjadikan pekan ini dipenuhi warna, musik, dan kenangan sejarah. **HUT Jakarta** bukan sekadar seremoni pemerintah, melainkan pesta budaya yang mengundang warga untuk kembali mengenali kota yang mereka tinggali.\n\nDari kampung tua hingga kawasan modern, Jakarta menampilkan wajahnya yang paling ekspresif di sepanjang bulan Juni, dan gema perayaannya masih terasa hingga pekan terakhir.\n\n## Betawi: Jiwa Budaya yang Terus Hidup\n\nDi jantung perayaan ini berdiri **budaya Betawi**, identitas asli masyarakat Jakarta yang lahir dari perpaduan berbagai bangsa selama berabad-abad.\n\nWarisan budaya yang kembali menjadi sorotan:\n\n- **Ondel-ondel** — boneka raksasa ikonik yang menjadi simbol kota.\n- **Gambang kromong** — musik yang memadukan pengaruh lokal dan Tionghoa.\n- **Lenong** — teater rakyat penuh humor dan kritik sosial.\n- **Kuliner khas** — kerak telor, soto Betawi, dan aneka jajanan tradisional.\n\nPerpaduan pengaruh Melayu, Arab, Tionghoa, India, dan Eropa dalam budaya Betawi adalah cerminan sejati Jakarta sebagai kota pertemuan banyak peradaban.\n\n## Seni dan Sejarah yang Berpadu\n\nMomen ulang tahun kota selalu menjadi ajang bagi seniman untuk berkarya. Sepanjang periode ini, berbagai ruang budaya di Jakarta biasanya menampilkan:\n\n1. **Pameran seni** yang mengangkat tema kota dan urban.\n2. **Pertunjukan musik dan tari** dari tradisional hingga kontemporer.\n3. **Wisata sejarah** di kawasan kota tua yang menyimpan jejak masa lampau.\n\nBagi warga, ini adalah undangan untuk memperlambat langkah dan melihat kembali bangunan-bangunan tua, gang-gang bersejarah, dan cerita yang kerap terlewat di tengah hiruk-pikuk keseharian.\n\n## Mengapa Perayaan Ini Penting\n\n> Sebuah kota tanpa memori budaya adalah kota tanpa jiwa.\n\nDi tengah pesatnya modernisasi, perayaan seperti ini berfungsi sebagai:\n\n- **Jangkar identitas** yang mengingatkan asal-usul kota.\n- **Ruang inklusi** yang merayakan keberagaman penduduknya.\n- **Panggung regenerasi** bagi seniman muda untuk menghidupkan tradisi.\n\n## Penutup\n\nMerayakan Jakarta berarti merayakan pertemuan—antara masa lalu dan masa kini, antara tradisi dan modernitas, antara ratusan latar belakang yang hidup berdampingan. Di pekan terakhir Juni ini, gema perayaan mengingatkan kita bahwa di balik gedung-gedung tinggi dan kepadatan lalu lintas, ada denyut budaya yang terus berdetak, menunggu untuk dirayakan.",
    "tier": "free"
  }
}
