{
  "publishAt": "2026-07-24T02:00:00.000Z",
  "market": "id",
  "date": "2026-07-24",
  "item": {
    "id": "id-20260724-news-1",
    "category": "news",
    "type": "text",
    "format": "markdown",
    "title": "Komdigi Verifikasi 14 Layanan Digital Apple: Babak Baru Perlindungan Anak di Ruang Digital Indonesia",
    "body": "Pemerintah Indonesia melalui Kementerian Komunikasi dan Digital (Komdigi) dilaporkan tengah melakukan proses verifikasi terhadap sejumlah layanan digital milik Apple, termasuk di antaranya iMessage dan peramban Safari. Langkah ini merupakan bagian dari upaya memastikan kepatuhan penyelenggara sistem elektronik terhadap standar perlindungan anak yang berlaku di Indonesia.\n\nPenting untuk dicatat bahwa proses ini bersifat administratif dan merupakan prosedur standar yang berlaku bagi semua penyelenggara platform digital, bukan tuduhan pelanggaran terhadap perusahaan tertentu.\n\n## Latar Belakang Kebijakan\n\nDalam beberapa tahun terakhir, Indonesia semakin serius menata ekosistem digitalnya, khususnya yang berkaitan dengan keamanan anak-anak di dunia maya. Pemerintah telah menerbitkan regulasi tata kelola penyelenggaraan sistem elektronik dalam perlindungan anak, yang mewajibkan platform digital untuk menerapkan sejumlah standar, antara lain:\n\n- **Verifikasi usia pengguna** yang lebih akurat dan bertanggung jawab\n- **Pengaturan privasi bawaan** yang berpihak pada keselamatan anak\n- **Pembatasan profilisasi data anak** untuk kepentingan komersial\n- **Mekanisme pelaporan konten** yang mudah diakses oleh anak dan orang tua\n\nRegulasi ini menempatkan Indonesia sejajar dengan sejumlah negara lain yang telah lebih dulu menerapkan aturan serupa, seperti Inggris dengan *Age Appropriate Design Code* dan Uni Eropa dengan *Digital Services Act*.\n\n## Apa yang Sedang Diverifikasi?\n\nMenurut informasi yang beredar di sejumlah pemberitaan, proses verifikasi mencakup 14 layanan digital yang dioperasikan Apple dan dapat diakses oleh pengguna di Indonesia. Beberapa layanan yang disebut antara lain:\n\n1. **iMessage** — layanan perpesanan yang terintegrasi di perangkat Apple\n2. **Safari** — peramban web bawaan pada iPhone, iPad, dan Mac\n3. **Layanan digital lainnya** yang menjadi bagian dari ekosistem Apple\n\nFokus verifikasi diperkirakan berkisar pada bagaimana layanan-layanan tersebut mengelola akses pengguna anak, fitur keamanan yang tersedia, serta kesesuaian kebijakan privasi dengan ketentuan yang berlaku di Indonesia.\n\nHingga artikel ini disusun, proses tersebut masih berjalan dan belum ada kesimpulan resmi mengenai hasilnya. Publik sebaiknya menunggu pernyataan resmi dari pihak berwenang maupun dari perusahaan terkait.\n\n## Mengapa Ini Penting bagi Asia Tenggara?\n\nIndonesia adalah salah satu pasar digital terbesar di Asia Tenggara dengan lebih dari 200 juta pengguna internet, dan sebagian besar di antaranya adalah anak-anak serta remaja. Langkah verifikasi terhadap perusahaan teknologi global menandai beberapa hal penting:\n\n### 1. Era Baru Regulasi Digital Regional\n\nKebijakan Indonesia berpotensi menjadi rujukan bagi negara-negara tetangga. Jika verifikasi semacam ini berjalan efektif, negara lain di kawasan dapat mengadopsi pendekatan serupa, menciptakan standar perlindungan anak yang lebih seragam di Asia Tenggara.\n\n### 2. Kesetaraan Perlakuan bagi Semua Platform\n\nProses ini menunjukkan bahwa regulasi berlaku bagi semua penyelenggara sistem elektronik, baik perusahaan lokal maupun raksasa teknologi global. Sebelumnya, sejumlah platform media sosial lain juga dilaporkan telah menjalani proses penilaian serupa.\n\n### 3. Perlindungan Anak sebagai Prioritas\n\nData dari berbagai lembaga menunjukkan bahwa anak-anak Indonesia mulai mengakses internet pada usia yang semakin muda. Tanpa pengaman yang memadai, mereka rentan terpapar konten yang tidak sesuai usia, perundungan siber, hingga penyalahgunaan data pribadi.\n\n## Bagaimana Posisi Apple?\n\nApple selama ini dikenal kerap menonjolkan aspek privasi dan keamanan sebagai nilai jual utamanya. Perusahaan tersebut telah menyediakan sejumlah fitur perlindungan keluarga, seperti:\n\n- **Screen Time** untuk mengatur durasi dan jenis penggunaan perangkat oleh anak\n- **Family Sharing** yang memungkinkan orang tua mengelola akun anak\n- **Communication Safety** yang membantu menyaring konten sensitif dalam perpesanan\n- **Pembatasan konten dan privasi** yang dapat disesuaikan pada tingkat perangkat\n\nProses verifikasi oleh regulator pada dasarnya bertujuan memastikan bahwa fitur-fitur semacam ini selaras dengan ketentuan hukum Indonesia, termasuk aspek teknis seperti verifikasi usia dan pengelolaan data pengguna anak.\n\n## Apa Artinya bagi Orang Tua dan Pengguna?\n\nBagi masyarakat umum, khususnya orang tua, perkembangan ini membawa beberapa implikasi positif:\n\n- **Standar keamanan yang lebih jelas.** Platform yang beroperasi di Indonesia dituntut memiliki mekanisme perlindungan anak yang dapat diverifikasi.\n- **Transparansi yang meningkat.** Proses regulasi mendorong perusahaan untuk lebih terbuka mengenai cara mereka menangani data dan keamanan pengguna muda.\n- **Peran orang tua tetap sentral.** Regulasi dan fitur teknologi hanyalah alat bantu; pendampingan langsung dari orang tua tetap menjadi lapisan perlindungan terpenting.\n\nBeberapa langkah praktis yang dapat dilakukan orang tua saat ini:\n\n1. Aktifkan fitur kontrol orang tua yang tersedia di perangkat anak.\n2. Buat akun anak sesuai usia sebenarnya agar sistem perlindungan berfungsi optimal.\n3. Diskusikan kebiasaan digital yang sehat secara rutin bersama anak.\n4. Manfaatkan pengaturan privasi untuk membatasi siapa yang dapat menghubungi anak.\n\n## Tantangan ke Depan\n\nPenerapan regulasi perlindungan anak di ruang digital bukan tanpa tantangan. Beberapa isu yang masih menjadi perdebatan di kalangan pakar antara lain:\n\n- **Keseimbangan antara privasi dan pengawasan.** Verifikasi usia yang ketat dapat bersinggungan dengan prinsip minimalisasi data.\n- **Kesiapan teknis lintas platform.** Setiap layanan memiliki arsitektur berbeda, sehingga penerapan standar seragam memerlukan waktu dan dialog berkelanjutan.\n- **Literasi digital masyarakat.** Regulasi hanya efektif jika diiringi pemahaman pengguna, terutama keluarga, tentang cara memanfaatkan fitur perlindungan yang tersedia.\n\n## Penutup\n\nVerifikasi layanan digital Apple oleh Komdigi menjadi penanda bahwa Indonesia kini memasuki fase yang lebih matang dalam tata kelola ruang digital. Alih-alih dilihat sebagai konfrontasi antara regulator dan perusahaan teknologi, proses ini lebih tepat dipahami sebagai dialog untuk memastikan bahwa kemajuan teknologi berjalan seiring dengan keselamatan generasi muda.\n\nPerkembangan selanjutnya patut dipantau, terutama bagaimana hasil verifikasi ini akan memengaruhi fitur dan kebijakan platform digital yang digunakan jutaan keluarga Indonesia setiap harinya.\n\n---\n\n*Artikel ini disusun berdasarkan informasi yang tersedia untuk publik dan bersifat informatif. Untuk perkembangan terbaru dan pernyataan resmi, silakan merujuk pada kanal komunikasi Kementerian Komunikasi dan Digital serta pihak-pihak terkait.*",
    "tier": "free"
  }
}
