{
  "publishAt": "2026-07-08T07:34:00.000Z",
  "market": "in",
  "date": "2026-07-08",
  "item": {
    "id": "in-20260708-tech-1",
    "category": "tech",
    "type": "text",
    "format": "markdown",
    "title": "भारत में 5जी नेटवर्क का विस्तार और डिजिटल समावेशन: एक नए युग की शुरुआत",
    "body": "## प्रस्तावना\n\nभारत में 5जी नेटवर्क अब केवल एक तकनीकी सपना नहीं रह गया है, बल्कि करोड़ों लोगों की रोज़मर्रा की ज़िंदगी का हिस्सा बनता जा रहा है। दिल्ली, मुंबई, बेंगलुरु, हैदराबाद और चेन्नई जैसे प्रमुख महानगरों में यह सेवा अब व्यापक रूप से उपलब्ध है, और धीरे-धीरे इसका दायरा छोटे शहरों तथा दूरदराज के ग्रामीण इलाकों तक भी फैल रहा है। यह विस्तार न सिर्फ़ इंटरनेट की रफ़्तार बढ़ा रहा है, बल्कि **डिजिटल समावेशन** की दिशा में एक निर्णायक कदम भी साबित हो रहा है।\n\n## 5जी क्या है और यह अलग क्यों है?\n\n5जी यानी पाँचवीं पीढ़ी की मोबाइल नेटवर्क तकनीक, अपने पिछले संस्करण 4जी की तुलना में कई गुना तेज़ और अधिक भरोसेमंद है। इसकी कुछ प्रमुख विशेषताएँ इस प्रकार हैं:\n\n- **अत्यधिक तेज़ गति:** डाउनलोड स्पीड 4जी की तुलना में 10 से 100 गुना तक अधिक हो सकती है।\n- **कम लेटेंसी (देरी):** नेटवर्क की प्रतिक्रिया लगभग तत्काल होती है, जो ऑनलाइन गेमिंग, वीडियो कॉल और रिमोट सर्जरी जैसी सेवाओं के लिए बेहद उपयोगी है।\n- **अधिक कनेक्शन क्षमता:** एक ही क्षेत्र में लाखों उपकरण एक साथ जुड़ सकते हैं, जो **IoT (इंटरनेट ऑफ़ थिंग्स)** के लिए आधार तैयार करता है।\n\n## शहरों से गाँवों तक: विस्तार की यात्रा\n\nशुरुआत में 5जी सेवा मुख्य रूप से बड़े महानगरों तक सीमित थी, लेकिन दूरसंचार कंपनियों के आक्रामक विस्तार और सरकारी नीतियों के सहयोग से अब यह तस्वीर तेज़ी से बदल रही है।\n\n| क्षेत्र | उपलब्धता की स्थिति |\n| --- | --- |\n| प्रमुख महानगर | व्यापक रूप से उपलब्ध |\n| टियर-2 और टियर-3 शहर | तेज़ी से विस्तार जारी |\n| ग्रामीण एवं दूरदराज इलाके | चरणबद्ध रूप से पहुँच रही सेवा |\n\nदूरदराज के इलाकों में नेटवर्क पहुँचाना आसान नहीं है। पहाड़ी क्षेत्रों, घने जंगलों और बिखरी हुई आबादी वाले गाँवों में टावर लगाना और फ़ाइबर बिछाना महँगा तथा चुनौतीपूर्ण होता है। फिर भी, सैटेलाइट-आधारित समाधानों और सार्वजनिक-निजी भागीदारी के ज़रिए यह अंतर लगातार कम हो रहा है।\n\n## डिजिटल समावेशन: सबके लिए अवसर\n\n5जी का सबसे बड़ा सामाजिक प्रभाव **डिजिटल खाई को पाटने** में है। जब गाँव-गाँव तक तेज़ इंटरनेट पहुँचता है, तो कई क्षेत्रों में क्रांतिकारी बदलाव संभव हो जाते हैं:\n\n1. **शिक्षा:** दूरस्थ गाँवों के छात्र भी उच्च गुणवत्ता वाली ऑनलाइन कक्षाओं और डिजिटल पुस्तकालयों तक पहुँच सकते हैं।\n2. **स्वास्थ्य सेवा:** टेलीमेडिसिन के माध्यम से मरीज़ बड़े शहरों के विशेषज्ञ डॉक्टरों से सीधे परामर्श ले सकते हैं।\n3. **कृषि:** किसान मौसम की सटीक जानकारी, बाज़ार भाव और स्मार्ट खेती तकनीकों का लाभ उठा सकते हैं।\n4. **रोज़गार:** दूर-दराज के युवाओं के लिए रिमोट वर्क और डिजिटल उद्यमिता के नए रास्ते खुलते हैं।\n\n## चुनौतियाँ और आगे की राह\n\nइस उज्ज्वल तस्वीर के साथ कुछ चुनौतियाँ भी जुड़ी हैं, जिन्हें नज़रअंदाज़ नहीं किया जा सकता:\n\n- **किफ़ायती उपकरण:** 5जी-सक्षम स्मार्टफ़ोन अभी भी हर वर्ग की पहुँच में नहीं हैं।\n- **डेटा की लागत:** ग्रामीण उपभोक्ताओं के लिए सस्ती डेटा योजनाएँ ज़रूरी हैं।\n- **डिजिटल साक्षरता:** केवल नेटवर्क पहुँचाना काफ़ी नहीं; लोगों को इसका सही उपयोग करना सिखाना भी अनिवार्य है।\n- **बुनियादी ढाँचा:** निरंतर बिजली आपूर्ति और स्थानीय भाषा में सामग्री की उपलब्धता भी अहम भूमिका निभाती है।\n\n## निष्कर्ष\n\nभारत में 5जी का विस्तार केवल एक तकनीकी उपलब्धि नहीं, बल्कि एक सामाजिक-आर्थिक परिवर्तन का इंजन है। जैसे-जैसे यह सेवा शहरों की सीमाओं से बाहर निकलकर गाँवों और दूरदराज के इलाकों तक पहुँच रही है, वैसे-वैसे **\"डिजिटल इंडिया\"** का सपना अधिक समावेशी और सशक्त होता जा रहा है। यदि उपकरणों की कीमत, डेटा की लागत और डिजिटल साक्षरता जैसी चुनौतियों पर मिलकर काम किया जाए, तो आने वाले वर्षों में 5जी हर भारतीय के लिए प्रगति और अवसर का द्वार खोल सकता है।",
    "tier": "free"
  }
}
