{
  "publishAt": "2026-07-04T17:01:00.000Z",
  "market": "sa",
  "date": "2026-07-04",
  "item": {
    "id": "sa-20260704-career",
    "category": "career",
    "type": "text",
    "format": "markdown",
    "title": "منتصف 2026 محطة مراجعة: كيف تعيد ضبط مسارك المهني في سوق عمل سعودي يتغير بسرعة؟",
    "body": "الأول من يوليو ليس مجرد يوم في التقويم؛ إنه منتصف السنة بالضبط — النقطة التي يملك فيها الموظف الطموح ما يكفي من بيانات عن أدائه في النصف الأول، وما يكفي من وقت لتصحيح المسار قبل نهاية العام. وفي سوق عمل يتحول بسرعة كسوق العمل السعودي، تصبح هذه المراجعة النصفية ضرورة لا رفاهية.\n\n## سوق يتغير من حولك\n\nخريطة الوظائف في المملكة اليوم مختلفة جذرياً عما كانت عليه قبل خمس سنوات: قطاعات السياحة والترفيه والفعاليات توظف بأعداد غير مسبوقة، وشركات التقنية والذكاء الاصطناعي تتنافس على الكفاءات، والمشاريع الكبرى تفتح آلاف الفرص في الإنشاءات والتشغيل والخدمات اللوجستية. في المقابل، ترتفع التوقعات: إتقان الأدوات الرقمية وأساسيات الذكاء الاصطناعي لم يعد ميزة إضافية، بل شرطاً ضمنياً في كثير من الأدوار.\n\n## خطة عملية للمراجعة النصفية\n\n1. **قيّم أهداف يناير بصدق**: اكتب ما خططت له مطلع العام وما تحقق فعلاً. الفجوة بينهما ليست فشلاً، بل بيانات تبني عليها النصف الثاني.\n2. **اعمل «جرداً» لمهاراتك**: اسأل نفسك: لو فتح باب التوظيف في شركتي غداً لوظيفتي نفسها، هل سأكون المرشح الأقوى؟ إن كان الجواب متردداً، فقد حددت أولوية النصف الثاني.\n3. **استثمر في مهارة واحدة كبيرة**: بدلاً من خمس دورات سطحية، اختر مهارة واحدة مطلوبة في سوقك — تحليل البيانات، إدارة المشاريع، أدوات الذكاء الاصطناعي التوليدي — وأتقنها عبر منصات مثل «دروب» وبرامج صندوق تنمية الموارد البشرية «هدف».\n4. **حدّث حضورك المهني**: سيرتك الذاتية وملفك على المنصات المهنية يجب أن يعكسا إنجازات النصف الأول بأرقام ملموسة، لا بأوصاف عامة.\n5. **افتح حواراً مع مديرك**: اجتماع منتصف العام فرصة لمواءمة التوقعات، وطرح طموحاتك في الترقية أو التطوير قبل أن تُحسم ميزانيات وخطط العام المقبل.\n\n## القاعدة الذهبية\n\nلا تنتظر ديسمبر لتكتشف أن العام مضى. من يراجع في يوليو يملك ستة أشهر كاملة للتنفيذ — ومن يؤجل، يملك الأماني فقط.",
    "tier": "free"
  }
}
