{
  "publishAt": "2026-06-30T04:59:00.000Z",
  "market": "jp",
  "date": "2026-06-30",
  "item": {
    "id": "jp-20260630-tech",
    "category": "tech",
    "type": "text",
    "format": "markdown",
    "title": "AIエージェント元年──「指示するAI」から「自ら動くAI」へ、私たちの仕事はどう変わるか",
    "body": "## チャットの次に来る「自律型AI」\n\n生成AIが文章や画像を作る道具として普及して数年。2026年のキーワードは間違いなく「AIエージェント」だ。質問に答えるだけのチャットボットとは異なり、エージェントは目標を与えられると、自ら計画を立て、複数のツールを使い分け、タスクを完了するまで動き続ける。\n\n「資料をまとめて」と頼めば、情報を検索し、要点を整理し、表計算ソフトにまとめ、メールの下書きまで用意する──そんな働き方が、現実の業務に入り込み始めている。\n\n## エージェントを支える三つの技術\n\nAIエージェントが実用段階に達した背景には、いくつかの技術的進展がある。\n\n1. **ツール連携(Function Calling)**:AIが外部のソフトウェアやデータベースを呼び出し、現実世界で操作を実行できるようになった。\n2. **長期記憶と文脈保持**:扱える情報量(コンテキスト)が飛躍的に拡大し、長い作業の流れを見失わなくなった。\n3. **自己検証のループ**:自らの出力を点検し、誤りを修正してから次へ進む仕組みが洗練された。\n\n## 期待と、向き合うべき課題\n\nもっとも、自律的に動くということは、誤った判断もそのまま実行してしまう危うさと表裏一体だ。\n\n- **信頼性**:重要な操作の前に人間の確認を挟む「ヒューマン・イン・ザ・ループ」の設計が欠かせない。\n- **セキュリティ**:外部ツールにアクセスする権限を、どこまで委ねるかの線引きが問われる。\n- **説明責任**:AIが下した判断の根拠をたどれる「透明性」の確保が求められる。\n\n## 「奪われる」のではなく「組み替える」\n\nエージェントの普及で、定型的な作業の多くは自動化されていくだろう。だが、それは仕事が消えることを必ずしも意味しない。むしろ、人間に求められる役割は「作業者」から、AIに適切な目標を与え、その成果を評価する「監督者・編集者」へと移っていく。\n\nAIを恐れるのでも、過信するのでもなく、優秀な部下に的確な指示を出すように使いこなす力。それが、これからの時代の新しいリテラシーになる。",
    "tier": "free"
  }
}
