{
  "publishAt": "2026-07-11T09:35:00.000Z",
  "market": "jp",
  "date": "2026-07-11",
  "item": {
    "id": "jp-20260711-tech-2",
    "category": "tech",
    "type": "text",
    "format": "markdown",
    "title": "Google、Gemini専用設計のノートPC「Googlebook」を発表——AIネイティブな体験で業界標準を狙う",
    "body": "Googleが、自社のAIモデル「Gemini」を最大限に活用することを前提に設計した新型ノートパソコン「Googlebook」を発表しました。これまでのパソコンが「アプリを起動して作業する道具」だったのに対し、GooglebookはAIが常に作業の文脈を理解し、ユーザーを支援する「AIネイティブ」な体験を掲げています。本記事では、発表内容のポイントと、業界に与えうる影響を整理します。\n\n## Googlebookとは何か\n\nGooglebookは、GeminiをOSレベルで深く統合したノートパソコンです。従来もブラウザやアプリ経由でAIアシスタントを利用することはできましたが、Googlebookでは文書作成、検索、画像編集、メール返信といった日常的な操作の中に、最初からAIが組み込まれている点が大きな違いです。\n\nユーザーが「何をしたいか」を伝えるだけで、複数のアプリをまたいだ作業をAIが補助してくれる——そんな体験を、ハードウェアとソフトウェアの両面から実現しようとする試みだと言えます。\n\n## 注目機能1：Magic Pointer\n\n今回の発表で特に注目を集めているのが「Magic Pointer」と呼ばれる新しい操作機能です。\n\nMagic Pointerは、画面上のテキスト、画像、UI要素などをポインターで指し示すだけで、Geminiがその対象を認識し、文脈に応じた操作候補を提示してくれる仕組みとされています。たとえば次のような使い方が想定されます。\n\n- 外国語の文章を指すと、その場で翻訳や要約を提案\n- 画像を指すと、編集・検索・共有などの選択肢を表示\n- 表やグラフを指すと、データの解説や別形式への変換を提案\n\n「コピーして別アプリに貼り付けてから処理する」という従来の手順を省き、目の前の対象に直接AIを適用できる点が、操作体験の大きな転換になりそうです。\n\n## 注目機能2：クロスデバイス連携\n\nもうひとつの柱がクロスデバイス機能です。Googlebookは、スマートフォンやタブレットなど、同じアカウントで利用している他のデバイスとの連携を重視して設計されています。\n\nスマートフォンで撮影した写真をすぐにGooglebook上で編集したり、外出先でスマートフォンに話しかけた内容の続きを、帰宅後にGooglebookで引き継いだりといった、デバイスの垣根を越えた作業の流れが想定されています。Geminiが「ユーザーが今何をしているか」をデバイス横断で把握することで、作業の分断を減らす狙いがあると見られます。\n\n## なぜ「業界標準」を狙えるのか\n\nパソコン業界では近年、各社がAI機能を搭載した製品を相次いで投入しており、AI処理を前提としたパソコンは大きなトレンドになっています。その中でGooglebookが持つ強みは、検索、メール、地図、動画など、多くの人が日常的に使うサービス群と同じ企業がAIとハードウェアを一体で設計している点です。\n\nサービス・AI・端末が同じ設計思想でつながることで、個別の機能追加では実現しにくい、一貫した体験を提供できる可能性があります。一方で、他社も独自のAI統合を急速に進めており、競争は今後さらに激しくなると考えられます。\n\n## 利用にあたって意識したいポイント\n\nAIが作業の文脈を理解するということは、それだけ多くの情報をAIが扱うことも意味します。導入を検討する際は、次のような点を確認しておくと安心です。\n\n- どのデータがAI処理の対象になるのか、設定で調整できるか\n- クロスデバイス連携の範囲を自分で管理できるか\n- 職場や学校で利用する場合の情報管理ルールとの整合性\n\nこうした設定を理解した上で使えば、AIネイティブな環境のメリットをより安全に享受できるでしょう。\n\n## まとめ\n\nGooglebookは、「AIを後から足す」のではなく「AIを前提に設計する」という発想を明確に打ち出した製品です。Magic Pointerによる直感的な操作と、クロスデバイス連携による作業の継続性は、今後のパソコンのあり方を占う試金石になりそうです。\n\n価格や発売時期、対応地域などの詳細は今後変わる可能性もあるため、購入を検討する場合は公式の最新情報を確認することをおすすめします。AI時代のパソコンがどのような形に落ち着いていくのか、引き続き各社の動向に注目です。",
    "tier": "free"
  }
}
