{
  "publishAt": "2026-07-01T07:42:21.326Z",
  "market": "vn",
  "date": "2026-07-01",
  "item": {
    "id": "vn-20260701-life",
    "category": "life",
    "type": "text",
    "format": "markdown",
    "title": "Trốn nóng cuối tháng 6: Gợi ý du lịch hè thông minh cho người Việt",
    "body": "## Mùa hè cao điểm đã đến\n\nTuần cuối tháng 6 là thời điểm nắng nóng gay gắt trên khắp cả nước, cũng là lúc nhu cầu đi du lịch, nghỉ dưỡng lên cao nhất trong năm. Thay vì chen chúc ở những điểm đông đúc, một chuyến đi được lên kế hoạch thông minh sẽ giúp bạn tận hưởng trọn vẹn kỳ nghỉ mà không \"cháy túi\".\n\n## Chọn điểm đến theo kiểu nghỉ dưỡng\n\n**Muốn biển xanh, cát trắng:** các bãi biển miền Trung và duyên hải vẫn là lựa chọn hàng đầu. Mẹo nhỏ: ưu tiên tắm biển sáng sớm hoặc chiều muộn để tránh tia UV mạnh nhất giữa trưa.\n\n**Muốn khí hậu mát mẻ:** vùng cao nguyên và núi phía Bắc mang lại không khí trong lành, nhiệt độ dễ chịu, phù hợp cho gia đình có trẻ nhỏ và người lớn tuổi.\n\n**Muốn gần nhà, tiết kiệm:** các khu du lịch sinh thái ven đô, suối và hồ tự nhiên là phương án lý tưởng cho chuyến đi ngắn trong ngày.\n\n## Mẹo đi hè mùa cao điểm\n\n- **Đặt sớm** vé và phòng để tránh giá tăng cao.\n- Đi **giữa tuần** nếu có thể — vắng người, giá tốt hơn.\n- Mang theo kem chống nắng, nước uống, mũ rộng vành và thuốc cơ bản.\n- Kiểm tra dự báo thời tiết trước 2–3 ngày để linh hoạt lịch trình.\n\n## Bảo vệ sức khỏe khi trời nóng\n\n> Uống đủ nước, hạn chế hoạt động mạnh vào khung 11h–15h, và để ý dấu hiệu say nắng như chóng mặt, buồn nôn.\n\nMột chuyến đi tuyệt vời không nằm ở việc bạn đi xa đến đâu, mà ở cảm giác thư giãn và những kỷ niệm mang về. Chúc bạn có một mùa hè mát lành và an toàn!",
    "tier": "free"
  }
}
