{
  "date": "2026-07-01",
  "items": [
    {
      "id": "kr-20260701-career",
      "category": "career",
      "type": "text",
      "format": "markdown",
      "title": "상반기가 끝나는 이 시점, 'AI 시대의 커리어'를 점검할 여섯 가지 질문",
      "body": "## 반환점에서 커리어를 멈춰 세우자\n\n2026년의 절반이 지나가고 있다. 연초에 세운 목표가 흐릿해지기 쉬운 6월 말은, 역설적으로 커리어를 다시 조준하기 좋은 시점이다. 특히 인공지능이 실무의 표준 도구로 자리 잡은 지금, '무엇을 잘하느냐'만큼 **'AI와 무엇을 함께 하느냐'** 가 경쟁력을 가른다.\n\n## 스스로에게 던져 볼 여섯 가지 질문\n\n1. **나의 업무 중 AI가 대신하기 쉬운 부분은?** — 위협이 아니라 '위임 목록'으로 보자. 반복 업무를 넘길수록 사람만의 판단에 쓸 시간이 늘어난다.\n2. **AI를 도구로 얼마나 능숙히 쓰는가?** — 프롬프트 작성, 결과 검증, 업무 자동화 세팅은 이제 문서 작성만큼 기본기가 됐다.\n3. **AI가 못 하는 나만의 강점은?** — 맥락 파악, 이해관계 조율, 신뢰 구축 같은 '사람의 일'이 어디에 있는지 적어 보자.\n4. **최근 6개월간 새로 배운 기술은?** — 배움이 멈춘 구간이 곧 위험 구간이다.\n5. **나의 성과를 숫자와 사례로 설명할 수 있는가?** — 이직·평가·협상의 언어는 결국 구체성이다.\n6. **1년 뒤 나는 어떤 문제를 푸는 사람이고 싶은가?** — 직함이 아니라 '해결하는 문제'로 방향을 잡자.\n\n## 하반기를 위한 실행 계획\n\n- **리스킬링(재교육)**: 데이터 해석, AI 협업, 도메인 전문성 중 '내 일과 맞닿은 하나'를 골라 깊게 판다.\n- **포트폴리오 갱신**: 상반기 성과를 사례 3개로 정리해 이력서·프로필에 즉시 반영한다.\n- **네트워크 점검**: 분기마다 업계 사람 두세 명과 대화하며 시장의 온도를 감지한다.\n\n> **핵심**: AI는 '내 자리를 빼앗는 존재'와 '내 역량을 증폭하는 도구' 사이 어딘가에 있다. 어느 쪽이 될지는, 반환점에 선 지금의 선택에 달려 있다.",
      "tier": "free"
    },
    {
      "id": "kr-20260701-culture",
      "category": "culture",
      "type": "text",
      "format": "markdown",
      "title": "'미술의 올림픽'이 열리는 여름 — 2026 베네치아 비엔날레를 읽는 법",
      "body": "## 2년에 한 번, 예술의 도시가 세계의 실험실이 된다\n\n이탈리아 베네치아에서는 올해 **국제 미술전 '베네치아 비엔날레'** 가 열리고 있다. 1895년 시작돼 한 세기가 넘는 역사를 가진 이 행사는 '미술계의 올림픽'으로 불린다. 봄에 문을 열어 11월까지 이어지는 만큼, 6월 넷째 주의 여름 여행자에게는 지금이 관람의 최적기다.\n\n## 비엔날레를 즐기는 세 개의 층위\n\n1. **본전시(중앙관·아르세날레)**: 총감독이 정한 주제 아래 전 세계 작가들의 작품이 한자리에 모인다. 그해 미술계가 던지는 '가장 큰 질문'이 담긴다.\n2. **국가관(자르디니)**: 각국이 자국을 대표하는 작가를 내세워 꾸미는 공간. 마치 예술로 겨루는 국가대표전 같아서, 나라별 개성과 사회적 화두를 비교하는 재미가 크다.\n3. **도시 전체의 병행 전시**: 유서 깊은 궁전과 성당, 골목 곳곳에서 열리는 부대 전시까지 더하면, 베네치아라는 도시 자체가 하나의 거대한 미술관이 된다.\n\n## 처음 가는 사람을 위한 관람 팁\n\n- **최소 이틀**: 자르디니와 아르세날레 두 축만 제대로 보려 해도 하루로는 벅차다. 무리한 완주보다 인상 깊은 작품에 머무는 편이 낫다.\n- **아침 일찍 입장**: 여름 성수기의 오후는 인파와 더위가 만만치 않다.\n- **주제 미리 읽기**: 그해의 총감독과 전시 주제를 알고 가면, 흩어져 보이던 작품들이 하나의 문장으로 꿰어진다.\n\n## 왜 지금 주목할 만한가\n\n비엔날레는 단순한 전시가 아니라 **동시대 예술이 어떤 문제와 씨름하고 있는지**를 보여 주는 지표다. 기후, 이주, 기술과 인간, 정체성 — 오늘의 세계가 품은 질문이 이미지와 설치로 번역돼 있다. 미술에 익숙하지 않아도, 지금 세계가 무엇을 고민하는지 궁금하다면 충분히 걸음할 이유가 된다.\n\n> **정리**: 여름 유럽 여행을 계획 중이라면, 베네치아의 물길 사이에 하루 이틀을 비워 두자. 2026년의 예술이 무엇을 말하는지 직접 마주할 기회다.",
      "tier": "free"
    },
    {
      "id": "kr-20260701-news",
      "category": "news",
      "type": "text",
      "format": "markdown",
      "title": "미국 중간선거 '예비선거의 여름'이 열렸다 — 11월을 향한 첫 신호들",
      "body": "## 왜 지금 미국인가\n\n2026년 11월 3일에 치러질 미국 중간선거는 하원 435석 전체와 상원 3분의 1, 그리고 다수의 주지사 자리를 다시 배분한다. 6월 넷째 주는 각 주의 **예비선거(프라이머리)**가 본격적으로 몰리는 시기로, 11월 본선의 구도를 미리 읽을 수 있는 '여름의 첫 신호'가 쏟아진다.\n\n## 이번 주 관전 포인트\n\n- **집권 여당의 중간 성적표**: 역사적으로 대통령 임기 중반의 중간선거는 여당에 불리하게 작동해 왔다. 물가·고용·금리에 대한 유권자 체감이 표심을 가르는 핵심 변수다.\n- **경합주(스윙 스테이트)의 후보 확정**: 애리조나, 조지아, 펜실베이니아 등 소수 표차로 승부가 갈리는 지역에서 어떤 성향의 후보가 살아남는지가 본선 전략을 좌우한다.\n- **경제 이슈의 전면화**: 인플레이션 둔화 속도, 주택 비용, 인공지능發 고용 변화가 지역별로 다르게 체감되면서 '한 나라 두 경제'라는 표현까지 등장했다.\n\n## 한국 독자에게 왜 중요한가\n\n미국 의회 지형은 통상·관세·반도체·전기차 보조금 등 한국 경제와 직결된 정책의 향방을 결정한다. 하원과 상원의 다수당이 어디로 기우느냐에 따라 대(對)한국 통상 기조와 공급망 정책의 온도가 달라질 수 있다.\n\n> **한 줄 요약**: 6월 말 예비선거는 '누가 이겼나'보다 '어떤 이슈가 표를 움직였나'를 보는 창이다. 물가와 일자리, 그리고 통상 정책 — 세 가지 키워드를 기억해 두자.\n\n## 앞으로의 일정\n\n여름 내내 이어지는 예비선거를 지나 9월부터는 본선 캠페인이 가열된다. 지금부터 후보 구도와 핵심 쟁점을 따라가면 11월의 결과를 훨씬 입체적으로 이해할 수 있다.",
      "tier": "free"
    },
    {
      "id": "kr-20260701-tech",
      "category": "tech",
      "type": "text",
      "format": "markdown",
      "title": "2026년, 휴머노이드 로봇이 '공장 밖'으로 나오기 시작했다",
      "body": "## 실험실을 벗어난 이족보행 로봇\n\n2026년 테크 업계의 가장 뜨거운 화두는 단연 **휴머노이드(인간형) 로봇**이다. 미국과 중국의 기업들이 앞다퉈 이족보행 로봇의 '대량 생산 원년'을 선언하면서, 그동안 시연 영상 속에만 존재하던 로봇이 실제 산업 현장과 물류 창고로 걸어 나오고 있다.\n\n## 무엇이 달라졌나\n\n과거 로봇 자동화가 '고정된 팔'의 반복 작업이었다면, 지금의 흐름은 세 가지 축이 결합된 결과다.\n\n1. **범용 AI 두뇌**: 대규모 언어·행동 모델이 로봇의 '눈과 판단'을 담당하면서, 정해진 코드가 아니라 자연어 지시로 새로운 작업을 학습한다.\n2. **하드웨어 원가 하락**: 액추에이터·배터리·센서 가격이 내려가며 '한 대 수억 원'이던 로봇이 산업용 차량 수준까지 근접했다.\n3. **데이터 플라이휠**: 현장에 배치된 로봇이 수집한 동작 데이터가 다시 모델을 학습시키는 선순환이 돌기 시작했다.\n\n## 어디에 먼저 쓰이나\n\n- **물류·제조**: 상자 옮기기, 부품 정렬처럼 사람이 기피하는 반복·중량 작업\n- **위험 환경**: 고온·분진·야간 작업 등 안전 사고 위험이 큰 공정\n- **서비스 실증**: 매장 재고 점검, 시설 순찰 등 제한된 실내 환경\n\n## 넘어야 할 벽\n\n기술 시연과 실사용 사이에는 여전히 간극이 크다. 배터리 지속시간, 손끝의 정밀 조작(그리퍼), 안전 인증, 그리고 무엇보다 **'투자 대비 실제 생산성'** 이 검증돼야 한다. 화려한 데모가 곧 상용화를 뜻하지 않는다는 점은 기억해 둘 만하다.\n\n> **정리**: 2026년은 휴머노이드 로봇의 '완성'이 아니라 '현장 데뷔'의 해다. 올해의 관전 포인트는 성능 자랑이 아니라, 몇 대가 실제로 일하며 돈값을 하는지다.",
      "tier": "free"
    }
  ],
  "updatedAt": "2026-07-01T10:13:02.494Z"
}
