{
  "publishAt": "2026-06-26T05:35:00.000Z",
  "market": "kr",
  "date": "2026-06-26",
  "item": {
    "id": "kr-20260626-career",
    "category": "career",
    "type": "text",
    "format": "markdown",
    "title": "AI 시대에 살아남는 커리어 전략: 'AI를 잘 쓰는 사람'으로 포지셔닝하기",
    "body": "## 질문이 바뀌었다\n\n\"AI가 내 일을 대체할까?\"라는 불안은 이제 더 실용적인 질문으로 바뀌고 있다. **\"나는 AI를 활용해 무엇을 더 잘할 수 있는가?\"** 변화의 한가운데에서 커리어를 지키고 키우는 사람들은, 도구를 두려워하는 대신 그 도구를 가장 잘 다루는 사람이 되는 길을 택한다.\n\n## 대체되는 일과 강화되는 일\n\nAI가 잘하는 영역과 사람의 가치가 빛나는 영역을 구분하는 것이 출발점이다.\n\n| AI가 대신하기 쉬운 일 | 사람의 가치가 커지는 일 |\n| --- | --- |\n| 반복적인 정보 정리·요약 | 모호한 문제를 정의하기 |\n| 정형화된 초안 작성 | 이해관계자 설득과 조율 |\n| 패턴이 명확한 분류·계산 | 맥락에 맞는 최종 판단 |\n\n핵심은 **\"실행\"의 일부가 자동화될수록, \"판단\"과 \"관계\"의 가치가 올라간다**는 점이다.\n\n## 지금 키워야 할 세 가지 역량\n\n### 1. 문제 정의력\n\nAI는 잘 정의된 문제를 빠르게 푼다. 그러나 \"무엇이 진짜 문제인가\"를 짚어내는 일은 여전히 사람의 몫이다. 좋은 질문을 던지는 능력이 그 어느 때보다 비싸졌다.\n\n### 2. 검증과 비판적 사고\n\nAI의 결과물은 그럴듯하지만 종종 틀린다. 결과를 그대로 받아들이지 않고 **사실 여부와 논리를 점검하는 능력**이 신뢰의 기준이 된다.\n\n### 3. 협업과 커뮤니케이션\n\n자동화가 진행될수록, 사람과 사람 사이를 잇는 역량은 자동화되지 않는다. 팀을 움직이고 신뢰를 만드는 일은 오히려 더 중요해진다.\n\n## 작게 시작하는 실천법\n\n1. 매주 자신의 업무 중 **반복적인 한 가지**를 골라 AI로 자동화해본다\n2. AI가 만든 결과를 **반드시 검토·수정**하며 자신의 판단을 덧붙인다\n3. 그 과정을 기록해 **\"나만의 활용 노하우\"** 로 축적한다\n\n> 미래의 경쟁력은 AI를 아느냐 모르느냐가 아니라, AI를 도구 삼아 어떤 판단과 가치를 더하느냐에서 갈린다.",
    "tier": "free"
  }
}
