{
  "publishAt": "2026-07-06T04:44:00.000Z",
  "market": "in",
  "date": "2026-07-06",
  "item": {
    "id": "in-20260706-career",
    "category": "career",
    "type": "text",
    "format": "markdown",
    "title": "GCC बूम: कैसे ग्लोबल कैपेबिलिटी सेंटर बन रहे हैं भारतीय अर्थव्यवस्था का नया ग्रोथ इंजन",
    "body": "बेंगलुरु, हैदराबाद और पुणे के चमचमाते टेक पार्कों में इन दिनों जो सबसे तेज़ी से बढ़ती कारोबारी कहानी लिखी जा रही है, उसका नाम है **GCC — ग्लोबल कैपेबिलिटी सेंटर**। दुनिया की दिग्गज कंपनियां अब भारत में सिर्फ़ काम \"आउटसोर्स\" नहीं कर रहीं, बल्कि अपने ख़ुद के रणनीतिक केंद्र खोल रही हैं — और यह बदलाव भारतीय बिज़नेस इकोसिस्टम की सूरत बदल रहा है।\n\n## GCC है क्या, और यह आउटसोर्सिंग से अलग क्यों है\n\nGCC किसी विदेशी कंपनी की भारत में अपनी **पूर्ण-स्वामित्व वाली इकाई** होती है, जो उसके ग्लोबल ऑपरेशंस के लिए काम करती है। पारंपरिक आउटसोर्सिंग में काम किसी तीसरी कंपनी को दिया जाता है; GCC मॉडल में कंपनी ख़ुद भारत में टीम बनाती है। फ़र्क़ बड़ा है — यहां बौद्धिक संपदा, अहम फ़ैसले और कोर प्रोडक्ट का काम कंपनी के भीतर ही रहता है।\n\nआंकड़े इस बूम की गवाही देते हैं: भारत में **1,700 से अधिक GCC** काम कर रहे हैं, जिनमें करीब **20 लाख प्रोफ़ेशनल्स** कार्यरत हैं। Fortune 500 की लगभग आधी कंपनियों का भारत में GCC है, और अनुमान है कि 2030 तक यह सेक्टर **100 अरब डॉलर** के पार पहुंच जाएगा।\n\n## 'बैक ऑफ़िस' से 'ब्रेन ऑफ़िस' तक\n\nसबसे अहम बदलाव काम की प्रकृति में आया है। दो दशक पहले ये केंद्र मुख्यतः कॉल सेंटर और डेटा प्रोसेसिंग तक सीमित थे। आज:\n\n- ग्लोबल बैंकों के **रिस्क मॉडल और ट्रेडिंग सिस्टम** भारत में बन रहे हैं\n- कार कंपनियों के **EV और ऑटोनॉमस ड्राइविंग** के इंजीनियरिंग सेंटर यहां हैं\n- रिटेल और फार्मा दिग्गजों की **AI और डेटा साइंस** टीमें भारत से चल रही हैं\n- कई GCC में ग्लोबल प्रोडक्ट्स के **चीफ़ आर्किटेक्ट और ग्लोबल रोल के लीडर** बैठते हैं\n\nयानी भारत अब \"सस्ता ठिकाना\" नहीं, बल्कि \"टैलेंट और इनोवेशन का ठिकाना\" के रूप में चुना जा रहा है।\n\n## टियर-2 शहरों की एंट्री: अगला बड़ा मोर्चा\n\nबेंगलुरु (सबसे बड़ा हब), हैदराबाद, पुणे, चेन्नई और NCR के बाद अब GCC की नई लहर **टियर-2 शहरों** की ओर बढ़ रही है — अहमदाबाद, कोयंबटूर, इंदौर, जयपुर, कोच्चि, भुवनेश्वर। वजहें साफ़ हैं: बड़े शहरों की तुलना में 25–30% कम लागत, कम एट्रिशन, और घर लौटना चाहने वाले अनुभवी प्रोफ़ेशनल्स की उपलब्धता।\n\nसरकारें भी होड़ में हैं — केंद्रीय बजट 2025 में टियर-2 शहरों में GCC को बढ़ावा देने के लिए राष्ट्रीय फ्रेमवर्क की घोषणा हुई, और कर्नाटक, उत्तर प्रदेश, मध्य प्रदेश, गुजरात जैसी राज्य सरकारें विशेष GCC नीतियों और इंसेंटिव के साथ कंपनियों को लुभा रही हैं।\n\n## कारोबारियों के लिए इसमें क्या अवसर है\n\nGCC बूम सिर्फ़ नौकरियों की कहानी नहीं है — यह पूरे बिज़नेस इकोसिस्टम के लिए मौका है:\n\n1. **रियल एस्टेट और को-वर्किंग**: ऑफ़िस स्पेस की मांग का सबसे बड़ा हिस्सा अब GCC से आ रहा है।\n2. **सर्विस प्रोवाइडर्स**: लीगल, HR, रिक्रूटमेंट, कंप्लायंस, IT इंफ्रा — हर GCC को स्थानीय पार्टनर चाहिए।\n3. **स्टार्टअप्स के लिए ग्राहक और साझेदार**: कई GCC भारतीय स्टार्टअप्स के साथ इनोवेशन पार्टनरशिप कर रहे हैं।\n4. **हॉस्पिटैलिटी और शहरी सेवाएं**: जहां GCC पहुंचते हैं, वहां हाउसिंग, ट्रांसपोर्ट, फ़ूड और लाइफस्टाइल बिज़नेस की पूरी सप्लाई चेन खड़ी होती है।\n\n## चुनौती भी समझिए\n\nतेज़ ग्रोथ के साथ चुनौतियां भी हैं — टैलेंट के लिए बढ़ती खींचतान और सैलरी वॉर, बड़े शहरों का इंफ्रास्ट्रक्चर दबाव, और AI ऑटोमेशन के दौर में शुरुआती स्तर की भूमिकाओं का बदलता स्वरूप। जो कंपनियां और प्रोफ़ेशनल्स AI-युग के हुनर — डेटा, ऑटोमेशन, डोमेन विशेषज्ञता — में निवेश करेंगे, फ़ायदा उन्हीं के हिस्से आएगा।\n\nकुल मिलाकर, GCC वह पुल है जिस पर चलकर ग्लोबल पूंजी, तकनीक और अवसर भारत आ रहे हैं — और 2026 में यह पुल पहले से कहीं ज़्यादा चौड़ा हो रहा है।",
    "tier": "free"
  }
}
